.editorconfig
.gitignore
.travis.yml
AUTHORS.rst
CONTRIBUTING.rst
HISTORY.rst
LICENSE
MANIFEST.in
Makefile
README.rst
requirements_dev.txt
setup.cfg
setup.py
tox.ini
.github/ISSUE_TEMPLATE.md
docs/Makefile
docs/authors.rst
docs/conf.py
docs/contributing.rst
docs/history.rst
docs/index.rst
docs/installation.rst
docs/make.bat
docs/readme.rst
docs/usage.rst
rest_framework_factory/__init__.py
rest_framework_factory/cli.py
rest_framework_factory/factory.py
rest_framework_factory.egg-info/PKG-INFO
rest_framework_factory.egg-info/SOURCES.txt
rest_framework_factory.egg-info/dependency_links.txt
rest_framework_factory.egg-info/entry_points.txt
rest_framework_factory.egg-info/not-zip-safe
rest_framework_factory.egg-info/requires.txt
rest_framework_factory.egg-info/top_level.txt
rest_framework_factory/__pycache__/__init__.cpython-36.pyc
rest_framework_factory/__pycache__/factory.cpython-36.pyc
rest_framework_factory/factory_ui/__init__.py
rest_framework_factory/skel/api.py.txt
rest_framework_factory/skel/filter.py.txt
rest_framework_factory/skel/form.py.txt
rest_framework_factory/skel/imports.py.txt
rest_framework_factory/skel/model.py.txt
rest_framework_factory/skel/register.py.txt
rest_framework_factory/skel/router.py.txt
rest_framework_factory/skel/serializer.py.txt
rest_framework_factory/skel/urlpatterns.py.txt
rest_framework_factory/skel/viewset.py.txt
tests/test_rest_framework_factory.py