Metadata-Version: 1.1
Name: rest-framework-factory
Version: 0.2.1
Summary: A factory for createing Django Rest Framework APIs
Home-page: https://github.com/MiddleFork/rest_framework_factory
Author: Steven Walker
Author-email: walker@mfgis.com
License: MIT license
Keywords: rest_framework_factory
Platform: UNKNOWN
Classifier: Development Status :: 2 - Pre-Alpha
Classifier: Intended Audience :: Developers
Classifier: License :: OSI Approved :: MIT License
Classifier: Natural Language :: English
Classifier: Programming Language :: Python :: 2
Classifier: Programming Language :: Python :: 2.7
Classifier: Programming Language :: Python :: 3
Classifier: Programming Language :: Python :: 3.4
Classifier: Programming Language :: Python :: 3.5
Classifier: Programming Language :: Python :: 3.6
Classifier: Programming Language :: Python :: 3.7
